helloworld.py
helloworldjcap-0.0.1.dist-info/LICENSE.txt
helloworldjcap-0.0.1.dist-info/METADATA
helloworldjcap-0.0.1.dist-info/WHEEL
helloworldjcap-0.0.1.dist-info/top_level.txt
helloworldjcap-0.0.1.dist-info/RECORD
